MANIFEST.in
README.md
setup.py
authy_admin/__init__.py
authy_admin/admin.py
authy_admin/forms.py
authy_admin/models.py
authy_admin/sites.py
authy_admin/templates/authy_admin/login.html
django_authy_admin.egg-info/PKG-INFO
django_authy_admin.egg-info/SOURCES.txt
django_authy_admin.egg-info/dependency_links.txt
django_authy_admin.egg-info/not-zip-safe
django_authy_admin.egg-info/requires.txt
django_authy_admin.egg-info/top_level.txt