Metadata-Version: 1.0
Name: django-authy-admin
Version: 0.0.2
Summary: A drop in replacement for django's default admin site that provides two-factor authentication via authy's REST API.
Home-page: http://github.com/jhmaddox/django-authy-admin/
Author: James Maddox
Author-email: jhmaddox@gmail.com
License: BSD
Platform: UNKNOWN
